LICENSE
README.md
setup.py
spynal/__init__.py
spynal/circstats.py
spynal/helpers.py
spynal/info.py
spynal/multi.py
spynal/plots.py
spynal/spikes.py
spynal/utils.py
spynal.egg-info/PKG-INFO
spynal.egg-info/SOURCES.txt
spynal.egg-info/dependency_links.txt
spynal.egg-info/not-zip-safe
spynal.egg-info/requires.txt
spynal.egg-info/top_level.txt
spynal/matIO/__init__.py
spynal/matIO/helpers.py
spynal/matIO/matIO.py
spynal/matIO/matIO_7.py
spynal/matIO/matIO_73.py
spynal/randstats/__init__.py
spynal/randstats/bootstrap.py
spynal/randstats/helpers.py
spynal/randstats/permutation.py
spynal/randstats/randstats.py
spynal/randstats/sampling.py
spynal/randstats/utils.py
spynal/spectra/__init__.py
spynal/spectra/bandfilter.py
spynal/spectra/helpers.py
spynal/spectra/multitaper.py
spynal/spectra/postprocess.py
spynal/spectra/preprocess.py
spynal/spectra/spectra.py
spynal/spectra/utils.py
spynal/spectra/wavelet.py
spynal/sync/__init__.py
spynal/sync/coherence.py
spynal/sync/helpers.py
spynal/sync/phasesync.py
spynal/sync/sync.py
spynal/tests/__init__.py
spynal/tests/data_fixtures.py
spynal/tests/test_circstats.py
spynal/tests/test_info.py
spynal/tests/test_matIO.py
spynal/tests/test_multi.py
spynal/tests/test_plots.py
spynal/tests/test_randstats.py
spynal/tests/test_spectra.py
spynal/tests/test_spikes.py
spynal/tests/test_spynal_install.py
spynal/tests/test_sync.py
spynal/tests/test_utils.py
spynal/tests/validity_test_circstats.py
spynal/tests/validity_test_info.py
spynal/tests/validity_test_multi.py
spynal/tests/validity_test_plots.py
spynal/tests/validity_test_randstats.py
spynal/tests/validity_test_spectra.py
spynal/tests/validity_test_spikes.py
spynal/tests/validity_test_sync.py