Metadata-Version: 2.1
Name: spynal
Version: 0.1.5
Summary: Simple Python Neural Analysis Library
Home-page: https://github.com/sbrincat/spynal.git
Author: ['Scott Brincat', 'John Tauber']
Author-email: sbrincat@mit.edu
License: LICENSE
Classifier: Intended Audience :: Science/Research
Classifier: License :: OSI Approved :: MIT License
Classifier: Programming Language :: Python :: 3.7
Classifier: Operating System :: POSIX :: Linux
Classifier: Operating System :: MacOS
License-File: LICENSE
Requires-Dist: numpy
Requires-Dist: scipy
Requires-Dist: pandas
Requires-Dist: matplotlib
Requires-Dist: h5py
Requires-Dist: hdf5storage
Requires-Dist: patsy
Requires-Dist: scikit-learn
Requires-Dist: torch
